icertx/__init__.py
icertx/api/__init__.py
icertx/api/chat_with_docs/__init__.py
icertx/api/chat_with_docs/answer_prompt_neo4j_retrieve_answer_prompt_post.py
icertx/api/debug/__init__.py
icertx/api/debug/read_root_get.py
icertx/api/get_started/__init__.py
icertx/api/get_started/test_api_key_test_api_key_get.py
icertx/api/neo_4_j/__init__.py
icertx/api/neo_4_j/generate_knowledge_graph_neo4j_knowledge_graph_post.py
icertx/api/project_estimation/__init__.py
icertx/api/project_estimation/project_estimation_estimate_project_estimation_post.py
icertx/client.py
icertx/errors.py
icertx/main.py
icertx/models/__init__.py
icertx/models/body_project_estimation_estimate_project_estimation_post.py
icertx/models/http_validation_error.py
icertx/models/project_estimation_answer.py
icertx/models/project_estimation_answer_result.py
icertx/models/prompt_answer.py
icertx/models/prompt_answer_result.py
icertx/models/prompt_input.py
icertx/models/validation_error.py
icertx/py.typed
icertx/types.py
icertx-0.1.0.dist-info/METADATA
icertx-0.1.0.dist-info/WHEEL
icertx-0.1.0.dist-info/RECORD
